azure/mgmt/storagepool/__init__.py
azure/mgmt/storagepool/_configuration.py
azure/mgmt/storagepool/_storage_pool_management.py
azure/mgmt/storagepool/_version.py
azure/mgmt/storagepool/aio/__init__.py
azure/mgmt/storagepool/aio/_configuration.py
azure/mgmt/storagepool/aio/_storage_pool_management.py
azure/mgmt/storagepool/aio/operations/__init__.py
azure/mgmt/storagepool/aio/operations/_disk_pool_zones_operations.py
azure/mgmt/storagepool/aio/operations/_disk_pools_operations.py
azure/mgmt/storagepool/aio/operations/_iscsi_targets_operations.py
azure/mgmt/storagepool/aio/operations/_operations.py
azure/mgmt/storagepool/aio/operations/_resource_skus_operations.py
azure/mgmt/storagepool/models/__init__.py
azure/mgmt/storagepool/models/_models.py
azure/mgmt/storagepool/models/_models_py3.py
azure/mgmt/storagepool/models/_storage_pool_management_enums.py
azure/mgmt/storagepool/operations/__init__.py
azure/mgmt/storagepool/operations/_disk_pool_zones_operations.py
azure/mgmt/storagepool/operations/_disk_pools_operations.py
azure/mgmt/storagepool/operations/_iscsi_targets_operations.py
azure/mgmt/storagepool/operations/_operations.py
azure/mgmt/storagepool/operations/_resource_skus_operations.py
azure_mgmt_storagepool-1.0.0.dist-info/METADATA
azure_mgmt_storagepool-1.0.0.dist-info/WHEEL
azure_mgmt_storagepool-1.0.0.dist-info/top_level.txt
azure_mgmt_storagepool-1.0.0.dist-info/RECORD
